igviz/__init__.py
igviz/igviz.py
igviz-0.5.1.dist-info/LICENSE
igviz-0.5.1.dist-info/METADATA
igviz-0.5.1.dist-info/WHEEL
igviz-0.5.1.dist-info/RECORD
